LICENSE.md
MANIFEST.in
README.md
pyproject.toml
setup.py
GluonixDesigner/Designer.py
GluonixDesigner.egg-info/PKG-INFO
GluonixDesigner.egg-info/SOURCES.txt
GluonixDesigner.egg-info/dependency_links.txt
GluonixDesigner.egg-info/entry_points.txt
GluonixDesigner.egg-info/requires.txt
GluonixDesigner.egg-info/top_level.txt
GluonixDesigner/Data/NGD.dll
GluonixDesigner/Data/Image/Add.png
GluonixDesigner/Data/Image/Align_Bottom.png
GluonixDesigner/Data/Image/Align_Center.png
GluonixDesigner/Data/Image/Align_Left.png
GluonixDesigner/Data/Image/Align_Right.png
GluonixDesigner/Data/Image/Align_Top.png
GluonixDesigner/Data/Image/Arrow_Left.png
GluonixDesigner/Data/Image/Arrow_Right.png
GluonixDesigner/Data/Image/Bar.png
GluonixDesigner/Data/Image/Black.png
GluonixDesigner/Data/Image/Button.png
GluonixDesigner/Data/Image/Canvas.png
GluonixDesigner/Data/Image/Canvas_Arc.png
GluonixDesigner/Data/Image/Canvas_Circle.png
GluonixDesigner/Data/Image/Canvas_Image.png
GluonixDesigner/Data/Image/Canvas_Line.png
GluonixDesigner/Data/Image/Canvas_Oval.png
GluonixDesigner/Data/Image/Canvas_Pie.png
GluonixDesigner/Data/Image/Canvas_Rectangle.png
GluonixDesigner/Data/Image/Canvas_RectangleR.png
GluonixDesigner/Data/Image/Canvas_Text.png
GluonixDesigner/Data/Image/Change.png
GluonixDesigner/Data/Image/Check.png
GluonixDesigner/Data/Image/Close.png
GluonixDesigner/Data/Image/Compare.png
GluonixDesigner/Data/Image/Compound.png
GluonixDesigner/Data/Image/Copy.png
GluonixDesigner/Data/Image/Cross_Black.png
GluonixDesigner/Data/Image/Cross_White.png
GluonixDesigner/Data/Image/Delete.png
GluonixDesigner/Data/Image/Entry.png
GluonixDesigner/Data/Image/Error.png
GluonixDesigner/Data/Image/Export.png
GluonixDesigner/Data/Image/Frame.png
GluonixDesigner/Data/Image/Grid_Lock.png
GluonixDesigner/Data/Image/Grid_Unlock.png
GluonixDesigner/Data/Image/Group.png
GluonixDesigner/Data/Image/Icon.ico
GluonixDesigner/Data/Image/Icon.png
GluonixDesigner/Data/Image/Image.png
GluonixDesigner/Data/Image/Label.png
GluonixDesigner/Data/Image/Line.png
GluonixDesigner/Data/Image/List.png
GluonixDesigner/Data/Image/Loading.gif
GluonixDesigner/Data/Image/Lock_Closed.png
GluonixDesigner/Data/Image/Lock_Open.png
GluonixDesigner/Data/Image/New.png
