Metadata-Version: 2.4
Name: GluonixDesigner
Version: 7.1
Summary: A GUI Designer with drag-and-drop features.
Author: Nucleon Automation
Author-email: Nucleon Automation <jagroop@nucleonautomation.com>
License: BSD 4-Clause License
License-File: LICENSE.md
Requires-Dist: pillow>=6.0.0
Dynamic: author
Dynamic: license-file
